audiostems/__init__.py
audiostems-1.0.1.dist-info/LICENSE
audiostems-1.0.1.dist-info/METADATA
audiostems-1.0.1.dist-info/WHEEL
audiostems-1.0.1.dist-info/entry_points.txt
audiostems-1.0.1.dist-info/top_level.txt
audiostems-1.0.1.dist-info/RECORD
