Metadata-Version: 2.1
Name: audiostems
Version: 1.0.1
Summary: Audio STEM Separation powered by Spleeter
Home-page: https://github.com/manjaroman/audiostems
Author: Manjaroman
Author-email: manjaroman@protonmail.com
License: UNKNOWN
Project-URL: Bug Tracker, https://github.com/manjaroman/audiostems/issues
Platform: UNKNOWN
Classifier: Programming Language :: Python :: 3
Classifier: License :: OSI Approved :: MIT License
Classifier: Operating System :: OS Independent
Requires-Python: <3.9,>=3.8
License-File: LICENSE
Requires-Dist: spleeter
Requires-Dist: youtube-dl
